{
  "title": "order (volatile part)",
  "id": "schemas/order/order_v",
  "$schema": "http://json-schema.org/draft-04/schema#",
  "javaType": "com.sos.joc.model.order.OrderV",
  "type": "object",
  "allOf": [
    {
      "description": "compact=true then ONLY path, id, jobChain, _type, surveyDate, state, processingState, runTimeIsTemporary, job(except blacklisted orders) are required and only title, processedBy, configurationStatus are optional",
      "required": [
        "path",
        "orderId",
        "jobChain",
        "surveyDate",
        "state",
        "processingState",
        "_type",
        "runTimeIsTemporary"
      ]
    },
    {
      "oneOf": [
        {
          "description": "pending order",
          "required": [
            "nextStartTime"
          ]
        },
        {
          "description": "running order",
          "required": [
            "historyId",
            "startedAt",
            "taskId",
            "inProcessSince"
          ]
        },
        {
          "description": "suspended, waitingForResource, blacklist order",
          "required": [
            "historyId",
            "startedAt"
          ]
        },
        {
          "description": "setback order",
          "required": [
            "historyId",
            "startedAt",
            "setback"
          ]
        }
      ]
    }
  ],
  "properties": {
    "path": {
      "$ref": "../common/path-schema.json"
    },
    "orderId": {
      "type": "string"
    },
    "jobChain": {
      "$ref": "../common/path-schema.json"
    },
    "priority": {
      "$ref": "../common/nonNegativeInteger-schema.json",
      "default": 0
    },
    "params": {
      "$ref": "../common/nameValuePairs-schema.json"
    },
    "_type": {
      "$ref": "orderType-schema.json"
    },
    "surveyDate": {
      "$ref": "../common/surveyDate_v-schema.json"
    },
    "state": {
      "description": "the name of the node",
      "type": "string"
    },
    "title": {
      "type": "string"
    },
    "job": {
      "description": "job path (required except blacklisted orders)",
      "$ref": "../common/path-schema.json"
    },
    "stateText": {
      "type": "string"
    },
    "configurationStatus": {
      "$ref": "../common/configurationStatus-schema.json"
    },
    "endState": {
      "description": "the name of the end node",
      "type": "string"
    },
    "processingState": {
      "$ref": "orderProcessingState-schema.json"
    },
    "nextStartTime": {
      "description": "ONLY for pending order or (waitingForResource order if processingState = job_not_in_period or node_delay)",
      "$ref": "../common/timestamp-schema.json"
    },
    "historyId": {
      "description": "for all orders except pending orders",
      "type": "string"
    },
    "startedAt": {
      "description": "for all orders except pending orders",
      "$ref": "../common/timestamp-schema.json"
    },
    "processedBy": {
      "description": "ONLY for running or blacklist order, contains Host/port of an active cluster member or URL of a JobScheduler Agent",
      "type": "string"
    },
    "taskId": {
      "description": "ONLY for running order",
      "type": "string"
    },
    "inProcessSince": {
      "description": "ONLY for running order",
      "$ref": "../common/timestamp-schema.json"
    },
    "setback": {
      "description": "ONLY for setback order",
      "$ref": "../common/timestamp-schema.json"
    },
    "lock": {
      "desciption": "lock path; ONLY for waitingForResource order if processingState = waiting_for_lock",
      "$ref": "../common/path-schema.json"
    },
    "processClass": {
      "desciption": "process class path; ONLY for waitingForResource order if processingState = waiting_for_process or waiting_for_agent",
      "$ref": "../common/path-schema.json"
    },
    "runTimeIsTemporary": {
      "type": "boolean",
      "default": false
    }
  }
}
